[
  {
    "id": "1781358267908-ygoa3",
    "status": "done",
    "voice": "en-US-GuyNeural",
    "engine": "piper",
    "rate": 1,
    "pitch": 0,
    "parts": 1,
    "wordCount": 3,
    "createdAt": "2026-06-13T13:44:27.910Z",
    "completedAt": "2026-06-13T13:44:40.776Z",
    "file": "1781358267908-ygoa3.zip",
    "error": null,
    "progress": 100
  },
  {
    "id": "1781367155174-4oebc",
    "status": "done",
    "voice": "en-US-JennyNeural",
    "engine": "edge",
    "rate": 1,
    "pitch": 0,
    "parts": 1,
    "wordCount": 28,
    "createdAt": "2026-06-13T16:12:35.178Z",
    "completedAt": "2026-06-13T16:12:45.651Z",
    "file": "1781367155174-4oebc.zip",
    "error": null,
    "progress": 100
  },
  {
    "id": "1781367222554-4s87q",
    "status": "done",
    "voice": "en_US-lessac-medium",
    "engine": "piper",
    "rate": 1,
    "pitch": 0,
    "parts": 1,
    "wordCount": 28,
    "createdAt": "2026-06-13T16:13:42.557Z",
    "completedAt": "2026-06-13T16:14:35.151Z",
    "file": "1781367222554-4s87q.zip",
    "error": null,
    "progress": 100
  }
]